[{"title":"Hello World","time":"2024-11-26","categories":"其它","description":"暂无简介","link":"/posts/1.html"},{"title":"Hello World","time":"2024-11-26","categories":"其它","description":"暂无简介","link":"/posts/1.html"},{"title":"Hello World","time":"2024-11-26","categories":"其它","description":"暂无简介","link":"/posts/1.html"},{"title":"Hello World","time":"2024-11-20","categories":"其它","description":"暂无简介","link":"/posts/1.html"},{"title":"Hello World","time":"2024-11-26","categories":"其它","description":"暂无简介","link":"/posts/1.html"}]